celery_pool_asyncio/__init__.py
celery_pool_asyncio/async_to_sync.py
celery_pool_asyncio/asynchronous.py
celery_pool_asyncio/beat.py
celery_pool_asyncio/coro_utils.py
celery_pool_asyncio/drainer.py
celery_pool_asyncio/environment_variables.py
celery_pool_asyncio/exceptions.py
celery_pool_asyncio/executors.py
celery_pool_asyncio/monkey.py
celery_pool_asyncio/monkey_utils.py
celery_pool_asyncio/pool.py
celery_pool_asyncio/scheduler.py
celery_pool_asyncio/signal_send.py
celery_pool_asyncio/tracer.py
celery_pool_asyncio/worker.py
celery_pool_asyncio/backends/__init__.py
celery_pool_asyncio/backends/amqp.py
celery_pool_asyncio/backends/rpc.py
celery_pool_asyncio-0.2.0.dist-info/LICENSE
celery_pool_asyncio-0.2.0.dist-info/METADATA
celery_pool_asyncio-0.2.0.dist-info/WHEEL
celery_pool_asyncio-0.2.0.dist-info/top_level.txt
celery_pool_asyncio-0.2.0.dist-info/zip-safe
celery_pool_asyncio-0.2.0.dist-info/RECORD
