Metadata-Version: 2.1
Name: celery-pool-asyncio
Version: 0.2.0
Summary: Celery pool to run coroutine tasks
Home-page: https://github.com/kai3341/celery-pool-asyncio
License: Apache Software License 2.0
Keywords: celery asyncio pool python3 background-jobs concurrency
Platform: UNKNOWN
Classifier: Development Status :: 4 - Beta
Classifier: Intended Audience :: Developers
Classifier: License :: OSI Approved :: Apache Software License
Classifier: Natural Language :: English
Classifier: Programming Language :: Python :: 3
Classifier: Programming Language :: Python :: 3.7
Classifier: Programming Language :: Python :: 3.8
